evo_downloader/__init__.py
evo_downloader/__main__.py
evo_downloader/base.py
evo_downloader/cli.py
evo_downloader/downloader.py
evo_downloader/utils.py
evo_downloader-1.0.7.dist-info/LICENSE
evo_downloader-1.0.7.dist-info/METADATA
evo_downloader-1.0.7.dist-info/WHEEL
evo_downloader-1.0.7.dist-info/entry_points.txt
evo_downloader-1.0.7.dist-info/top_level.txt
evo_downloader-1.0.7.dist-info/RECORD
