Metadata-Version: 2.1
Name: evo_downloader
Version: 1.0.7
Summary: Awesome evo_downloader created by maycuatroi
Home-page: https://github.com/maycuatroi/evo_downloader/
Author: maycuatroi
License-File: LICENSE
Requires-Dist: requests
Requires-Dist: rich
Requires-Dist: click
Requires-Dist: humanize
Requires-Dist: types-requests
Provides-Extra: test
Requires-Dist: pytest ; extra == 'test'
Requires-Dist: coverage ; extra == 'test'
Requires-Dist: flake8 ; extra == 'test'
Requires-Dist: black ; extra == 'test'
Requires-Dist: isort ; extra == 'test'
Requires-Dist: pytest-cov ; extra == 'test'
Requires-Dist: codecov ; extra == 'test'
Requires-Dist: mypy ; extra == 'test'
Requires-Dist: gitchangelog ; extra == 'test'
Requires-Dist: mkdocs ; extra == 'test'
